pro2/__init__.py
pro2/models.py
pro2/outcli.py
101703378_project2-0.0.2.dist-info/METADATA
101703378_project2-0.0.2.dist-info/WHEEL
101703378_project2-0.0.2.dist-info/entry_points.txt
101703378_project2-0.0.2.dist-info/top_level.txt
101703378_project2-0.0.2.dist-info/RECORD
