Metadata-Version: 2.1
Name: 101703378-project2
Version: 0.0.2
Summary: Removing outliers from a pandas dataframe
Home-page: UNKNOWN
Author: Nitin
Author-email: nnitin_be17@thapar.edu
License: UNKNOWN
Platform: UNKNOWN
Requires-Python: >=2.7
